prompt_poet/__init__.py
prompt_poet/pp_exceptions.py
prompt_poet/prompt.py
prompt_poet/template.py
prompt_poet/template_registry.py
prompt_poet/tokenizer.py
prompt_poet/examples/cai.yml.j2
prompt_poet/examples/cai_helpers.py
prompt_poet/examples/macros/global_settings.yml.j2
prompt_poet/examples/sections/bod_timestamp.yml.j2
prompt_poet/examples/sections/cai_message_pins.yml.j2
prompt_poet/examples/sections/cai_messages.yml.j2
prompt_poet/examples/sections/character_definition.yml.j2
prompt_poet/examples/sections/persona_definition.yml.j2
prompt_poet/examples/sections/reply_prompt.yml.j2
prompt_poet/examples/sections/validate_inputs.yml.j2
spoonia_prompt_poet-0.0.44.dist-info/LICENSE
spoonia_prompt_poet-0.0.44.dist-info/METADATA
spoonia_prompt_poet-0.0.44.dist-info/WHEEL
spoonia_prompt_poet-0.0.44.dist-info/top_level.txt
spoonia_prompt_poet-0.0.44.dist-info/RECORD
