Metadata-Version: 2.1
Name: spoonia_prompt_poet
Version: 0.0.44
Summary: Streamlines and simplifies prompt design for both developers and non-technical users with a low code approach.
Home-page: https://github.com/spoonia/prompt-poet
Author: Sandeep Poonia
Author-email: sandeep.poonia.90@gmail.com
License: MIT
Requires-Python: >=3.10
License-File: LICENSE
Requires-Dist: jinja2 >=3.0.0
Requires-Dist: PyYaml >=6.0.0
Requires-Dist: cachetools ==5.3.3
Requires-Dist: tiktoken ==0.7.0
